medusa/__init__.py
medusa/embedding/__init__.py
medusa/exception/MetricNotSupportedError.py
medusa/exception/ModelNotSupportedError.py
medusa/exception/MoreThanOneFaceError.py
medusa/exception/UnsupportedFormatError.py
medusa/exception/__init__.py
medusa/model/__init__.py
medusa/model/age_detection.py
medusa/model/cnn.py
medusa/model/emotion_detection.py
medusa/model/face_embedding.py
medusa/model/gender_detection.py
medusa/model/vgg16_face.py
medusa/model/util/__init__.py
medusa/model/util/distance.py
medusa/model/util/image_show.py
medusa/model/util/postprocessor.py
medusa/model/util/preprocessor.py
medusa/test/__init__.py
medusa/test/_webcam_test.py
medusa/vision/__init__.py
medusa/vision/age.py
medusa/vision/emotion.py
medusa/vision/face.py
medusa/vision/gender.py
medusa/vision/recognize.py
medusa_resources/__init__.py
medusa_resources/exception/ResourceDownloadError.py
medusa_resources/exception/RollbackError.py
medusa_resources/exception/__init__.py
medusa_resources/storage/__init__.py
medusa_resources/storage/storage_manager.py
medusa_resources/util/__init__.py
medusa_resources/util/find_file.py
medusa_resources/util/logger.py
medusa_vision-0.7.5.dist-info/LICENSE
medusa_vision-0.7.5.dist-info/METADATA
medusa_vision-0.7.5.dist-info/WHEEL
medusa_vision-0.7.5.dist-info/entry_points.txt
medusa_vision-0.7.5.dist-info/top_level.txt
medusa_vision-0.7.5.dist-info/RECORD
