Metadata-Version: 2.1
Name: medusa-vision
Version: 0.7.5
Summary: A light-weight facial attribute recognition and face embedding calculation library.
Home-page: https://github.com/vortezwohl/medusa-vision
Author: vortezwohl
Author-email: vortezwohl@proton.me
License: GNU GENERAL PUBLIC LICENSE
Project-URL: Bug Tracker, https://github.com/vortezwohl/medusa-vision/issues
Classifier: Programming Language :: Python :: 3
Classifier: Operating System :: OS Independent
Classifier: Natural Language :: English
Requires-Python: >=3.6
License-File: LICENSE
Requires-Dist: opencv-python>=4.10.0.84
Requires-Dist: keras>=3.4.1
Requires-Dist: numpy>=1.26.4
Requires-Dist: tensorflow>=2.16.2
Requires-Dist: gdown>=5.2.0
